fastsms/__init__.py
fastsms/main.py
fastsms-0.1.0.dist-info/METADATA
fastsms-0.1.0.dist-info/WHEEL
fastsms-0.1.0.dist-info/RECORD
