Metadata-Version: 2.3
Name: fastsms
Version: 0.1.0
Summary: Lightning-Fast Messaging API for Modern Businesses
Author: Md Sulaiman
Author-email: dev.suliman@icloud.com
Requires-Python: >=3.9
Classifier: Programming Language :: Python :: 3
Classifier: Programming Language :: Python :: 3.9
Classifier: Programming Language :: Python :: 3.10
Classifier: Programming Language :: Python :: 3.11
Classifier: Programming Language :: Python :: 3.12
Classifier: Programming Language :: Python :: 3.13
Requires-Dist: readyapi (>=0.112.0,<0.113.0)
Requires-Dist: uvicorn (>=0.34.3,<0.35.0)
